{"name":"AssetcategoryService","version":"62","methods":[{"serviceName":"AssetcategoryService","method":"POST","path":"/assetcategory/add-category","parameters":[{"name":"title","type":"string"},{"name":"vocabularyId","type":"long"},{"name":"serviceContext","type":"object<com.liferay.portal.service.ServiceContext>"}],"actionName":"addCategory"},{"serviceName":"AssetcategoryService","method":"POST","path":"/assetcategory/add-category","parameters":[{"name":"parentCategoryId","type":"long"},{"name":"titleMap","type":"map<string,string>"},{"name":"descriptionMap","type":"map<string,string>"},{"name":"vocabularyId","type":"long"},{"name":"categoryProperties","type":"string[]"},{"name":"serviceContext","type":"object<com.liferay.portal.service.ServiceContext>"}],"actionName":"addCategory"},{"serviceName":"AssetcategoryService","method":"POST","path":"/assetcategory/delete-categories","parameters":[{"name":"categoryIds","type":"long[]"}],"actionName":"deleteCategories"},{"serviceName":"AssetcategoryService","method":"POST","path":"/assetcategory/delete-categories","parameters":[{"name":"categoryIds","type":"long[]"},{"name":"serviceContext","type":"object<com.liferay.portal.service.ServiceContext>"}],"actionName":"deleteCategories"},{"serviceName":"AssetcategoryService","method":"POST","path":"/assetcategory/delete-category","parameters":[{"name":"categoryId","type":"long"}],"actionName":"deleteCategory"},{"serviceName":"AssetcategoryService","method":"GET","path":"/assetcategory/get-categories","parameters":[{"name":"className","type":"string"},{"name":"classPK","type":"long"}],"actionName":"getCategories"},{"serviceName":"AssetcategoryService","method":"GET","path":"/assetcategory/get-category","parameters":[{"name":"categoryId","type":"long"}],"actionName":"getCategory"},{"serviceName":"AssetcategoryService","method":"GET","path":"/assetcategory/get-child-categories","parameters":[{"name":"parentCategoryId","type":"long"}],"actionName":"getChildCategories"},{"serviceName":"AssetcategoryService","method":"GET","path":"/assetcategory/get-child-categories","parameters":[{"name":"parentCategoryId","type":"long"},{"name":"start","type":"int"},{"name":"end","type":"int"},{"name":"obc","type":"object<com.liferay.portal.kernel.util.OrderByComparator>"}],"actionName":"getChildCategories"},{"serviceName":"AssetcategoryService","method":"GET","path":"/assetcategory/get-json-search","parameters":[{"name":"groupId","type":"long"},{"name":"name","type":"string"},{"name":"vocabularyIds","type":"long[]"},{"name":"start","type":"int"},{"name":"end","type":"int"}],"actionName":"getJsonSearch"},{"serviceName":"AssetcategoryService","method":"GET","path":"/assetcategory/get-json-vocabulary-categories","parameters":[{"name":"vocabularyId","type":"long"},{"name":"start","type":"int"},{"name":"end","type":"int"},{"name":"obc","type":"object<com.liferay.portal.kernel.util.OrderByComparator>"}],"actionName":"getJsonVocabularyCategories"},{"serviceName":"AssetcategoryService","method":"GET","path":"/assetcategory/get-json-vocabulary-categories","parameters":[{"name":"groupId","type":"long"},{"name":"title","type":"string"},{"name":"vocabularyId","type":"long"},{"name":"start","type":"int"},{"name":"end","type":"int"},{"name":"obc","type":"object<com.liferay.portal.kernel.util.OrderByComparator>"}],"actionName":"getJsonVocabularyCategories"},{"serviceName":"AssetcategoryService","method":"GET","path":"/assetcategory/get-vocabulary-categories","parameters":[{"name":"vocabularyId","type":"long"},{"name":"start","type":"int"},{"name":"end","type":"int"},{"name":"obc","type":"object<com.liferay.portal.kernel.util.OrderByComparator>"}],"actionName":"getVocabularyCategories"},{"serviceName":"AssetcategoryService","method":"GET","path":"/assetcategory/get-vocabulary-categories","parameters":[{"name":"parentCategoryId","type":"long"},{"name":"vocabularyId","type":"long"},{"name":"start","type":"int"},{"name":"end","type":"int"},{"name":"obc","type":"object<com.liferay.portal.kernel.util.OrderByComparator>"}],"actionName":"getVocabularyCategories"},{"serviceName":"AssetcategoryService","method":"GET","path":"/assetcategory/get-vocabulary-categories","parameters":[{"name":"groupId","type":"long"},{"name":"name","type":"string"},{"name":"vocabularyId","type":"long"},{"name":"start","type":"int"},{"name":"end","type":"int"},{"name":"obc","type":"object<com.liferay.portal.kernel.util.OrderByComparator>"}],"actionName":"getVocabularyCategories"},{"serviceName":"AssetcategoryService","method":"GET","path":"/assetcategory/get-vocabulary-categories-count","parameters":[{"name":"groupId","type":"long"},{"name":"vocabularyId","type":"long"}],"actionName":"getVocabularyCategoriesCount"},{"serviceName":"AssetcategoryService","method":"GET","path":"/assetcategory/get-vocabulary-categories-count","parameters":[{"name":"groupId","type":"long"},{"name":"name","type":"string"},{"name":"vocabularyId","type":"long"}],"actionName":"getVocabularyCategoriesCount"},{"serviceName":"AssetcategoryService","method":"GET","path":"/assetcategory/get-vocabulary-categories-display","parameters":[{"name":"vocabularyId","type":"long"},{"name":"start","type":"int"},{"name":"end","type":"int"},{"name":"obc","type":"object<com.liferay.portal.kernel.util.OrderByComparator>"}],"actionName":"getVocabularyCategoriesDisplay"},{"serviceName":"AssetcategoryService","method":"GET","path":"/assetcategory/get-vocabulary-categories-display","parameters":[{"name":"groupId","type":"long"},{"name":"name","type":"string"},{"name":"vocabularyId","type":"long"},{"name":"start","type":"int"},{"name":"end","type":"int"},{"name":"obc","type":"object<com.liferay.portal.kernel.util.OrderByComparator>"}],"actionName":"getVocabularyCategoriesDisplay"},{"serviceName":"AssetcategoryService","method":"GET","path":"/assetcategory/get-vocabulary-root-categories","parameters":[{"name":"vocabularyId","type":"long"},{"name":"start","type":"int"},{"name":"end","type":"int"},{"name":"obc","type":"object<com.liferay.portal.kernel.util.OrderByComparator>"}],"actionName":"getVocabularyRootCategories"},{"serviceName":"AssetcategoryService","method":"GET","path":"/assetcategory/get-vocabulary-root-categories","parameters":[{"name":"groupId","type":"long"},{"name":"vocabularyId","type":"long"},{"name":"start","type":"int"},{"name":"end","type":"int"},{"name":"obc","type":"object<com.liferay.portal.kernel.util.OrderByComparator>"}],"actionName":"getVocabularyRootCategories"},{"serviceName":"AssetcategoryService","method":"GET","path":"/assetcategory/get-vocabulary-root-categories-count","parameters":[{"name":"groupId","type":"long"},{"name":"vocabularyId","type":"long"}],"actionName":"getVocabularyRootCategoriesCount"},{"serviceName":"AssetcategoryService","method":"POST","path":"/assetcategory/move-category","parameters":[{"name":"categoryId","type":"long"},{"name":"parentCategoryId","type":"long"},{"name":"vocabularyId","type":"long"},{"name":"serviceContext","type":"object<com.liferay.portal.service.ServiceContext>"}],"actionName":"moveCategory"},{"serviceName":"AssetcategoryService","method":"POST","path":"/assetcategory/search","parameters":[{"name":"groupId","type":"long"},{"name":"name","type":"string"},{"name":"categoryProperties","type":"string[]"},{"name":"start","type":"int"},{"name":"end","type":"int"}],"actionName":"search"},{"serviceName":"AssetcategoryService","method":"POST","path":"/assetcategory/search","parameters":[{"name":"groupIds","type":"long[]"},{"name":"title","type":"string"},{"name":"vocabularyIds","type":"long[]"},{"name":"start","type":"int"},{"name":"end","type":"int"}],"actionName":"search"},{"serviceName":"AssetcategoryService","method":"POST","path":"/assetcategory/search","parameters":[{"name":"groupId","type":"long"},{"name":"keywords","type":"string"},{"name":"vocabularyId","type":"long"},{"name":"start","type":"int"},{"name":"end","type":"int"},{"name":"obc","type":"object<com.liferay.portal.kernel.util.OrderByComparator>"}],"actionName":"search"},{"serviceName":"AssetcategoryService","method":"POST","path":"/assetcategory/update-category","parameters":[{"name":"categoryId","type":"long"},{"name":"parentCategoryId","type":"long"},{"name":"titleMap","type":"map<string,string>"},{"name":"descriptionMap","type":"map<string,string>"},{"name":"vocabularyId","type":"long"},{"name":"categoryProperties","type":"string[]"},{"name":"serviceContext","type":"object<com.liferay.portal.service.ServiceContext>"}],"actionName":"updateCategory"}]}