{"name":"MembershiprequestService","version":"62","module":"mobile.sdk","methods":[{"serviceName":"MembershiprequestService","method":"POST","path":"/membershiprequest/add-membership-request","parameters":[{"name":"groupId","type":"long"},{"name":"comments","type":"string"},{"name":"serviceContext","type":"object<com.liferay.portal.service.ServiceContext>"}],"actionName":"addMembershipRequest"},{"serviceName":"MembershiprequestService","method":"POST","path":"/membershiprequest/delete-membership-requests","parameters":[{"name":"groupId","type":"long"},{"name":"statusId","type":"int"}],"actionName":"deleteMembershipRequests"},{"serviceName":"MembershiprequestService","method":"GET","path":"/membershiprequest/get-membership-request","parameters":[{"name":"membershipRequestId","type":"long"}],"actionName":"getMembershipRequest"},{"serviceName":"MembershiprequestService","method":"POST","path":"/membershiprequest/update-status","parameters":[{"name":"membershipRequestId","type":"long"},{"name":"reviewComments","type":"string"},{"name":"statusId","type":"int"},{"name":"serviceContext","type":"object<com.liferay.portal.service.ServiceContext>"}],"actionName":"updateStatus"}]}